pyxhook
xmacros
