Metadata-Version: 1.0
Name: pyxmacros
Version: 0.7
Summary: A library to create macros on a linux system
Home-page: https://gitlab.alelec.net/corona/pyxmacros
Author: Andrew Leech
Author-email: andrew@alelec.net
License: BSD
Platform: UNKNOWN
